pygstudio/__init__.py
pygstudio/__main__.py
pygstudio/_template/engine.py
pygstudio/_template/globals.py
pygstudio/_template/main_game.py
pygstudio/_template/script_manager.py
pygstudio/_template/components/__init__.py
pygstudio_flamfrosticboio-1.0.1.dist-info/LICENSE
pygstudio_flamfrosticboio-1.0.1.dist-info/METADATA
pygstudio_flamfrosticboio-1.0.1.dist-info/WHEEL
pygstudio_flamfrosticboio-1.0.1.dist-info/top_level.txt
pygstudio_flamfrosticboio-1.0.1.dist-info/RECORD
