Metadata-Version: 2.1
Name: pygstudio_flamfrosticboio
Version: 1.0.1
Summary: A simple format with tools to help build games easily with pygame.
Author-email: flamfrosticboio <ffe.jhexe@gmail.com>
Project-URL: Homepage, https://github.com/flamfrosticboio/pygstudio
Project-URL: Issues, https://github.com/flamfrosticboio/pygstudio/issues
Classifier: Programming Language :: Python :: 3
Classifier: License :: OSI Approved :: Apache Software License
Classifier: Operating System :: OS Independent
Classifier: Intended Audience :: Developers
Requires-Python: >=3.8
License-File: LICENSE
